pybatteryid/__init__.py
pybatteryid/basisfunctions.py
pybatteryid/dataclasses.py
pybatteryid/identification.py
pybatteryid/inputdesign.py
pybatteryid/l1regls.py
pybatteryid/modelstructure.py
pybatteryid/plotter.py
pybatteryid/regression.py
pybatteryid/simulation.py
pybatteryid/typeddicts.py
pybatteryid/utilities.py
pybatteryid/voltage.py
pybatteryid-3.0.0.dist-info/licenses/LICENSE.txt
pybatteryid-3.0.0.dist-info/METADATA
pybatteryid-3.0.0.dist-info/WHEEL
pybatteryid-3.0.0.dist-info/top_level.txt
pybatteryid-3.0.0.dist-info/RECORD
