Metadata-Version: 2.4
Name: pybatteryid
Version: 3.0.0
Summary: Data-driven Battery Model Identification in Python
Home-page: https://github.com/muizabdul29/PyBatteryID
Author: Muiz Sheikh
Classifier: Programming Language :: Python :: 3
Classifier: Operating System :: OS Independent
License-File: LICENSE.txt
Requires-Dist: numpy>=2.1.0
Requires-Dist: cvxopt
Requires-Dist: scikit-learn
Requires-Dist: rich
Requires-Dist: matplotlib
Dynamic: author
Dynamic: classifier
Dynamic: description
Dynamic: description-content-type
Dynamic: home-page
Dynamic: license-file
Dynamic: requires-dist
Dynamic: summary
